MANIFEST.in
README.rst
setup.py
data_conversion/VERSION
data_conversion/__init__.py
data_conversion/cmdline.py
data_conversion/run_async.py
data_conversion/run_sync.py
data_conversion/settings.py
data_conversion.egg-info/PKG-INFO
data_conversion.egg-info/SOURCES.txt
data_conversion.egg-info/dependency_links.txt
data_conversion.egg-info/entry_points.txt
data_conversion.egg-info/not-zip-safe
data_conversion.egg-info/requires.txt
data_conversion.egg-info/top_level.txt
data_conversion/data_convert/__init__.py
data_conversion/data_convert/core.py
data_conversion/data_convert/data_mock.py
data_conversion/data_convert/model.py
data_conversion/data_convert/mongo_io.py
data_conversion/data_convert/util.py
data_conversion/db/__init__.py
data_conversion/db/mongo.py
data_conversion/utils/__init__.py
data_conversion/utils/custom_convert.py
tests/__init__.py
tests/py3-ignores.txt
tests/requirements.txt
tests/test_data_conversion.py