Metadata-Version: 1.2
Name: data-conversion
Version: 0.0.4
Summary: A ETL framework to convert data
Home-page: https://github.com/xiaowangwindow/data-conversion
Author: Alex Wang
Maintainer: Alex Wang
Maintainer-email: xiaowangwindow@163.com
License: BSD
Platform: UNKNOWN
Classifier: Intended Audience :: Developers
Classifier: License :: OSI Approved :: BSD License
Classifier: Operating System :: OS Independent
Classifier: Programming Language :: Python
Classifier: Programming Language :: Python :: 3.5
Classifier: Topic :: Internet :: WWW/HTTP
Classifier: Topic :: Software Development :: Libraries :: Python Modules
